pysick/__init__.py
pysick/_messagebox_pysick.py
pysick/_tkinter_pysick.py
pysick/graphics.py
pysick/image.py
pysick/pysick_core.py
pysick/assets/blue_icon_2k.png
pysick/assets/logo_blue.ico
pysick/assets/logo_red.ico
pysick/assets/logo_yellow.ico
pysick/assets/outdated_logo.ico
pysick/assets/red_icon_2k.png
pysick/assets/yellow_icon_2k.png
pysick-15.0.0.dist-info/LICENSE
pysick-15.0.0.dist-info/METADATA
pysick-15.0.0.dist-info/WHEEL
pysick-15.0.0.dist-info/top_level.txt
pysick-15.0.0.dist-info/RECORD
