Metadata-Version: 2.1
Name: pysick
Version: 15.0.0
Summary: A lightweight 2D game framework using Tkinter, A super duper Video Player using 
Home-page: https://github.com/COWZIIK/pysick
Author: CowZik
Author-email: cowzik@email.com
License: MIT
Classifier: Programming Language :: Python :: 3
Classifier: License :: OSI Approved :: MIT License
License-File: LICENSE
